{
    "id": "item_spaceship_intelligence",
    "icon": "/public/images/item/itemiconbig/item_spaceship_intelligence.png",
    "name": "情报档案",
    "description": "成套线索整合而成的情报档案，可用于各类地区行动。",
    "rarity": 4,
    "type": 57,
    "obtainWayIds": [
        "item_obtain_spaceship_intelligence"
    ],
    "obtainWays": [
        {
            "id": "item_obtain_spaceship_intelligence",
            "desc": "帝江号-会客室线索搜集",
            "bindSystem": 404,
            "phaseId": "Map",
            "phaseArgs": "{\r\n  \"instId\": \"mark_ss_reception_teleport9800000031\"\r\n}",
            "icon": "/public/images/item/itemtips/icon_tips_trd.png"
        }
    ],
    "tutorials": [],
    "craft": null,
    "droppedBy": []
}