{
  "weaponId": "wpn_claym_0003",
  "title": "工业零点一",
  "rarity": 4,
  "weapontype": 3,
  "icon": "public/images/weapon/icon/wpn_claym_0003.png",
  "iconbig": "public/images/weapon/iconbig/wpn_claym_0003.png",
  "iconfull": "public/images/weapon/full/wpn_claym_0003.png",
  "desc": "终末地干员用武器，装备之后可以显著提升干员的作战能力。",
  "decoDesc": "在开拓区常见的一种武器类型，基础设计已难以追溯。这种武器制造工艺并不复杂，常见工业设备都可生产。",
  "baseAtk": [
    34,
    38,
    41,
    45,
    48,
    52,
    55,
    59,
    62,
    65,
    69,
    72,
    76,
    79,
    83,
    86,
    90,
    93,
    96,
    100,
    103,
    107,
    110,
    114,
    117,
    121,
    124,
    127,
    131,
    134,
    138,
    141,
    145,
    148,
    152,
    155,
    158,
    162,
    165,
    169,
    172,
    176,
    179,
    183,
    186,
    189,
    193,
    196,
    200,
    203,
    207,
    210,
    214,
    217,
    220,
    224,
    227,
    231,
    234,
    238,
    241,
    245,
    248,
    251,
    255,
    258,
    262,
    265,
    269,
    272,
    276,
    279,
    282,
    286,
    289,
    293,
    296,
    300,
    303,
    307,
    310,
    313,
    317,
    320,
    324,
    327,
    331,
    334,
    338,
    341
  ],
  "skilllist": [
    {
      "skillName": "力量提升·小",
      "description": "力量<@ba.vup>+{str}</>",
      "blackboard": [
        {
          "key": "str",
          "value": [
            12,
            21,
            31,
            40,
            50,
            60,
            69,
            79,
            93
          ]
        }
      ]
    },
    {
      "skillName": "攻击提升·小",
      "description": "攻击力<@ba.vup>+{atk:0.0%}</>",
      "blackboard": [
        {
          "key": "atk",
          "value": [
            0.03,
            0.054,
            0.078,
            0.102,
            0.126,
            0.15,
            0.174,
            0.198,
            0.234
          ]
        }
      ]
    },
    {
      "skillName": "压制·应急强化",
      "description": "装备者的战技命中敌人时，获得攻击力<@ba.vup>+{atk_up:0.0%}</>，持续{duration:0}秒。\n<@ba.info>同名效果无法叠加。</>",
      "blackboard": [
        {
          "key": "atk_up",
          "value": [
            0.12,
            0.144,
            0.168,
            0.192,
            0.216,
            0.24,
            0.264,
            0.288,
            0.336
          ]
        },
        {
          "key": "duration",
          "value": [
            20,
            20,
            20,
            20,
            20,
            20,
            20,
            20,
            20
          ]
        }
      ]
    }
  ],
  "weaponDesc": "我不是第一次听他们提到“文明的食腐动物”这个话题，只是我还没有亲眼见过。\n很多人难以理解，塔卫二的生活充满了困难。城市与社区之间需要团结一致才能渡过难关，但仍然有不少人选择离开城市，过着流浪者和投机者的生活。\n但是我并不会感到奇怪，有些人失去得太多了。就像我上周采访的那十几位难民，他们的社区遭遇了灾害，食物严重短缺，根本没有选择。\n但也有一部分人，他们单纯地不愿意遵守某种秩序，或是天生坏种，他们自愿生活在暴力和危险之中。\n但归根究底，他们无法摆脱“文明”本身。我上周看到这些人正在使用捡来的机械工具制造武器，我真的很好奇，他们是从哪里弄到一台完整的车床的。然而，最终的答案其实很简单，他们会从城市的垃圾堆中碰碰运气，找到他们所需的一切。\n“文明的食腐动物”这个说法非常贴切，对吧？\n顺便提一下，报社的那个小记者，下次不要让她跟着我。她这一辈子就应该待在围墙后面，生活在城市里。一个连睡袋都难以接受的人，不应该在开拓区乱跑。老老实实去当个明星跟班更适合她。"
}