{
  "weaponId": "wpn_claym_0010",
  "title": "达尔霍夫7",
  "rarity": 3,
  "weapontype": "Claymores",
  "icon": "/public/images/weapon/icon/wpn_claym_0010.png",
  "iconbig": "/public/images/weapon/iconbig/wpn_claym_0010.png",
  "iconfull": "/public/images/weapon/full/wpn_claym_0010.png",
  "desc": "终末地干员用武器，装备之后可以显著提升干员的作战能力。",
  "decoDesc": "终末地工业制造的干员基础装备之一。由武库工程师达尔霍夫负责设计。该设计为攻坚任务提供装备选择。",
  "baseAtk": [],
  "skilllist": [
    {
      "skillName": "主能力提升·小",
      "description": "主能力值<@ba.vup>+{mainattr}</>",
      "blackboard": [
        {
          "key": "mainattr",
          "value": [
            10.0,
            18.0,
            26.0,
            34.0,
            42.0,
            51.0,
            59.0,
            67.0,
            79.0
          ]
        }
      ]
    },
    {
      "skillName": "强攻·武装整备",
      "description": "攻击力<@ba.vup>+{atk_up:0}</>。",
      "blackboard": [
        {
          "key": "atk_up",
          "value": [
            12.0,
            14.399999618530273,
            16.799999237060547,
            19.200000762939453,
            21.600000381469727,
            24.0,
            26.399999618530273,
            28.799999237060547,
            33.599998474121094
          ]
        }
      ]
    }
  ],
  "weaponDesc": "我们认为，在一支由十二名干员组成的整编行动小队中，至少需要两到三名干员装备适用于近身战的重型武器。这些干员必须具备极高的战斗素养、强韧的心理素质，以及丰富的经验——他们将负责为小队实现包括攻坚与突破在内的高风险任务目标。由于天使对终末地设施的威胁程度日益加剧，我们必须重设训练标准，提高实战模拟强度，对小队的人员构成做出调整，具体方案如下……"
}