{
  "templateId": "eny_0071_sandb",
  "name": "斧甲兽",
  "icon": "/public/images/enemy/monstericon/eny_0071_sandb.png",
  "iconbig": "/public/images/enemy/monstericonbig/eny_0071_sandb.png",
  "enemyTag": "",
  "rarity": 1,
  "技能描述": [
    "愤怒的斧甲兽会把一切闯入领地的敌人用巨角驱赶出去，一定要小心它的冲撞。",
    "会进行各种大范围的攻击，在它愤怒时及时打断。"
  ],
  "描述": "自然环境中的野生斧甲兽，身披骨甲。在冲锋状态下，其斧状巨角甚至能破开厚重的合金门。",
  "处决承伤系数": 1.5,
  "物理承伤系数": 1,
  "自然承伤系数": 1,
  "寒冷承伤系数": 1,
  "电磁承伤系数": 1,
  "灼热承伤系数": 1,
  "超域承伤系数": 1,
  "物理抗性系数": 1,
  "自然抗性系数": 1,
  "寒冷抗性系数": 1,
  "电磁抗性系数": 1,
  "灼热抗性系数": 1,
  "超域抗性系数": 1,
  "普通攻击范围": 7,
  "失衡值上限": 280,
  "失衡恢复时间": 9,
  "失衡时护甲值": 30,
  "失衡节点": "0.50",
  "处决技力回复": 50,
  "重量": 2,
  "对塔攻击值": 20,
  "初始护甲": 30,
  "最大韧性": 65,
  "回弹系数": 0.3,
  "受伤韧性降低": 0,
  "韧性完全回复时长": 0,
  "韧性回复值": 0,
  "韧性回复间隔": 0,
  "韧性归零时护甲值": 0,
  "变种": [
    {
      "enemyId": "eny_0071_sandb",
      "templateId": "eny_0071_sandb",
      "attrModifiers": "",
      "最大生命值": [
        1385,
        1580,
        1787,
        2006,
        2237,
        2626,
        3057,
        3534,
        4059,
        4635,
        4960,
        5291,
        5883,
        6511,
        7176,
        7876,
        8613,
        9051,
        9492,
        9936,
        10928,
        11998,
        13150,
        14389,
        15720,
        17149,
        18682,
        20467,
        22389,
        24457,
        27590,
        30361,
        33371,
        36640,
        40187,
        44032,
        48199,
        52709,
        57590,
        62869,
        68041,
        73547,
        79403,
        85626,
        92232,
        99239,
        106664,
        114528,
        122848,
        131644,
        143357,
        152574,
        162311,
        172595,
        183455,
        194921,
        207024,
        219799,
        233279,
        247504,
        262658,
        277803,
        294290,
        310746,
        327947,
        345031,
        363584,
        381990,
        404016,
        427763,
        443559,
        458756,
        475295,
        491199,
        508497,
        525125,
        543200,
        560567,
        579435,
        595357,
        623137,
        651842,
        681492,
        712106,
        743705,
        776307,
        809933,
        844605,
        880341,
        917164,
        939625,
        962441,
        985614,
        1009146,
        1024715,
        1040402,
        1056207,
        1072131,
        1088173,
        1104334
      ],
      "攻击力": [
        66,
        75,
        85,
        96,
        107,
        118,
        129,
        141,
        153,
        166,
        179,
        192,
        205,
        219,
        233,
        248,
        263,
        278,
        294,
        310,
        328,
        345,
        364,
        382,
        401,
        421,
        441,
        461,
        482,
        503,
        546,
        584,
        625,
        668,
        712,
        758,
        807,
        857,
        910,
        965,
        1022,
        1081,
        1143,
        1207,
        1274,
        1343,
        1414,
        1489,
        1565,
        1645,
        1735,
        1820,
        1908,
        2000,
        2094,
        2152,
        2212,
        2272,
        2333,
        2395,
        2462,
        2528,
        2597,
        2664,
        2735,
        2805,
        2878,
        2949,
        3026,
        3102,
        3152,
        3201,
        3252,
        3301,
        3352,
        3401,
        3453,
        3503,
        3554,
        3604,
        3656,
        3708,
        3760,
        3812,
        3865,
        3918,
        3970,
        4023,
        4076,
        4130,
        4180,
        4231,
        4283,
        4334,
        4381,
        4428,
        4476,
        4524,
        4572,
        4620
      ],
      "防御力": [
        100,
        100,
        100,
        100,
        100,
        100,
        100,
        100,
        100,
        100,
        100,
        100,
        100,
        100,
        100,
        100,
        100,
        100,
        100,
        100,
        100,
        100,
        100,
        100,
        100,
        100,
        100,
        100,
        100,
        100,
        100,
        100,
        100,
        100,
        100,
        100,
        100,
        100,
        100,
        100,
        100,
        100,
        100,
        100,
        100,
        100,
        100,
        100,
        100,
        100,
        100,
        100,
        100,
        100,
        100,
        100,
        100,
        100,
        100,
        100,
        100,
        100,
        100,
        100,
        100,
        100,
        100,
        100,
        100,
        100,
        100,
        100,
        100,
        100,
        100,
        100,
        100,
        100,
        100,
        100,
        100,
        100,
        100,
        100,
        100,
        100,
        100,
        100,
        100,
        100,
        100,
        100,
        100,
        100,
        100,
        100,
        100,
        100,
        100,
        100
      ]
    },
    {
      "enemyId": "eny_0071_sandb_NoAssault",
      "templateId": "eny_0071_sandb",
      "attrModifiers": "",
      "最大生命值": [
        1385,
        1580,
        1787,
        2006,
        2237,
        2626,
        3057,
        3534,
        4059,
        4635,
        4960,
        5291,
        5883,
        6511,
        7176,
        7876,
        8613,
        9051,
        9492,
        9936,
        10928,
        11998,
        13150,
        14389,
        15720,
        17149,
        18682,
        20467,
        22389,
        24457,
        27590,
        30361,
        33371,
        36640,
        40187,
        44032,
        48199,
        52709,
        57590,
        62869,
        68041,
        73547,
        79403,
        85626,
        92232,
        99239,
        106664,
        114528,
        122848,
        131644,
        143357,
        152574,
        162311,
        172595,
        183455,
        194921,
        207024,
        219799,
        233279,
        247504,
        262658,
        277803,
        294290,
        310746,
        327947,
        345031,
        363584,
        381990,
        404016,
        427763,
        443559,
        458756,
        475295,
        491199,
        508497,
        525125,
        543200,
        560567,
        579435,
        595357,
        623137,
        651842,
        681492,
        712106,
        743705,
        776307,
        809933,
        844605,
        880341,
        917164,
        939625,
        962441,
        985614,
        1009146,
        1024715,
        1040402,
        1056207,
        1072131,
        1088173,
        1104334
      ],
      "攻击力": [
        66,
        75,
        85,
        96,
        107,
        118,
        129,
        141,
        153,
        166,
        179,
        192,
        205,
        219,
        233,
        248,
        263,
        278,
        294,
        310,
        328,
        345,
        364,
        382,
        401,
        421,
        441,
        461,
        482,
        503,
        546,
        584,
        625,
        668,
        712,
        758,
        807,
        857,
        910,
        965,
        1022,
        1081,
        1143,
        1207,
        1274,
        1343,
        1414,
        1489,
        1565,
        1645,
        1735,
        1820,
        1908,
        2000,
        2094,
        2152,
        2212,
        2272,
        2333,
        2395,
        2462,
        2528,
        2597,
        2664,
        2735,
        2805,
        2878,
        2949,
        3026,
        3102,
        3152,
        3201,
        3252,
        3301,
        3352,
        3401,
        3453,
        3503,
        3554,
        3604,
        3656,
        3708,
        3760,
        3812,
        3865,
        3918,
        3970,
        4023,
        4076,
        4130,
        4180,
        4231,
        4283,
        4334,
        4381,
        4428,
        4476,
        4524,
        4572,
        4620
      ],
      "防御力": [
        100,
        100,
        100,
        100,
        100,
        100,
        100,
        100,
        100,
        100,
        100,
        100,
        100,
        100,
        100,
        100,
        100,
        100,
        100,
        100,
        100,
        100,
        100,
        100,
        100,
        100,
        100,
        100,
        100,
        100,
        100,
        100,
        100,
        100,
        100,
        100,
        100,
        100,
        100,
        100,
        100,
        100,
        100,
        100,
        100,
        100,
        100,
        100,
        100,
        100,
        100,
        100,
        100,
        100,
        100,
        100,
        100,
        100,
        100,
        100,
        100,
        100,
        100,
        100,
        100,
        100,
        100,
        100,
        100,
        100,
        100,
        100,
        100,
        100,
        100,
        100,
        100,
        100,
        100,
        100,
        100,
        100,
        100,
        100,
        100,
        100,
        100,
        100,
        100,
        100,
        100,
        100,
        100,
        100,
        100,
        100,
        100,
        100,
        100,
        100
      ]
    },
    {
      "enemyId": "eny_0071_sandb_activityspecial_01",
      "templateId": "eny_0071_sandb",
      "attrModifiers": "",
      "最大生命值": [
        1385,
        1580,
        1787,
        2006,
        2237,
        2626,
        3057,
        3534,
        4059,
        4635,
        4960,
        5291,
        5883,
        6511,
        7176,
        7876,
        8613,
        9051,
        9492,
        9936,
        10928,
        11998,
        13150,
        14389,
        15720,
        17149,
        18682,
        20467,
        22389,
        24457,
        27590,
        30361,
        33371,
        36640,
        40187,
        44032,
        48199,
        52709,
        57590,
        62869,
        68041,
        73547,
        79403,
        85626,
        92232,
        99239,
        106664,
        114528,
        122848,
        131644,
        143357,
        152574,
        162311,
        172595,
        183455,
        194921,
        207024,
        219799,
        233279,
        247504,
        262658,
        277803,
        294290,
        310746,
        327947,
        345031,
        363584,
        381990,
        404016,
        427763,
        443559,
        458756,
        475295,
        491199,
        508497,
        525125,
        543200,
        560567,
        579435,
        595357,
        623137,
        651842,
        681492,
        712106,
        743705,
        776307,
        809933,
        844605,
        880341,
        917164,
        939625,
        962441,
        985614,
        1009146,
        1024715,
        1040402,
        1056207,
        1072131,
        1088173,
        1104334
      ],
      "攻击力": [
        66,
        75,
        85,
        96,
        107,
        118,
        129,
        141,
        153,
        166,
        179,
        192,
        205,
        219,
        233,
        248,
        263,
        278,
        294,
        310,
        328,
        345,
        364,
        382,
        401,
        421,
        441,
        461,
        482,
        503,
        546,
        584,
        625,
        668,
        712,
        758,
        807,
        857,
        910,
        965,
        1022,
        1081,
        1143,
        1207,
        1274,
        1343,
        1414,
        1489,
        1565,
        1645,
        1735,
        1820,
        1908,
        2000,
        2094,
        2152,
        2212,
        2272,
        2333,
        2395,
        2462,
        2528,
        2597,
        2664,
        2735,
        2805,
        2878,
        2949,
        3026,
        3102,
        3152,
        3201,
        3252,
        3301,
        3352,
        3401,
        3453,
        3503,
        3554,
        3604,
        3656,
        3708,
        3760,
        3812,
        3865,
        3918,
        3970,
        4023,
        4076,
        4130,
        4180,
        4231,
        4283,
        4334,
        4381,
        4428,
        4476,
        4524,
        4572,
        4620
      ],
      "防御力": [
        100,
        100,
        100,
        100,
        100,
        100,
        100,
        100,
        100,
        100,
        100,
        100,
        100,
        100,
        100,
        100,
        100,
        100,
        100,
        100,
        100,
        100,
        100,
        100,
        100,
        100,
        100,
        100,
        100,
        100,
        100,
        100,
        100,
        100,
        100,
        100,
        100,
        100,
        100,
        100,
        100,
        100,
        100,
        100,
        100,
        100,
        100,
        100,
        100,
        100,
        100,
        100,
        100,
        100,
        100,
        100,
        100,
        100,
        100,
        100,
        100,
        100,
        100,
        100,
        100,
        100,
        100,
        100,
        100,
        100,
        100,
        100,
        100,
        100,
        100,
        100,
        100,
        100,
        100,
        100,
        100,
        100,
        100,
        100,
        100,
        100,
        100,
        100,
        100,
        100,
        100,
        100,
        100,
        100,
        100,
        100,
        100,
        100,
        100,
        100
      ]
    },
    {
      "enemyId": "eny_0071_sandb_activityspecial_02",
      "templateId": "eny_0071_sandb",
      "attrModifiers": "",
      "最大生命值": [
        1385,
        1580,
        1787,
        2006,
        2237,
        2626,
        3057,
        3534,
        4059,
        4635,
        4960,
        5291,
        5883,
        6511,
        7176,
        7876,
        8613,
        9051,
        9492,
        9936,
        10928,
        11998,
        13150,
        14389,
        15720,
        17149,
        18682,
        20467,
        22389,
        24457,
        27590,
        30361,
        33371,
        36640,
        40187,
        44032,
        48199,
        52709,
        57590,
        62869,
        68041,
        73547,
        79403,
        85626,
        92232,
        99239,
        106664,
        114528,
        122848,
        131644,
        143357,
        152574,
        162311,
        172595,
        183455,
        194921,
        207024,
        219799,
        233279,
        247504,
        262658,
        277803,
        294290,
        310746,
        327947,
        345031,
        363584,
        381990,
        404016,
        427763,
        443559,
        458756,
        475295,
        491199,
        508497,
        525125,
        543200,
        560567,
        579435,
        595357,
        623137,
        651842,
        681492,
        712106,
        743705,
        776307,
        809933,
        844605,
        880341,
        917164,
        939625,
        962441,
        985614,
        1009146,
        1024715,
        1040402,
        1056207,
        1072131,
        1088173,
        1104334
      ],
      "攻击力": [
        66,
        75,
        85,
        96,
        107,
        118,
        129,
        141,
        153,
        166,
        179,
        192,
        205,
        219,
        233,
        248,
        263,
        278,
        294,
        310,
        328,
        345,
        364,
        382,
        401,
        421,
        441,
        461,
        482,
        503,
        546,
        584,
        625,
        668,
        712,
        758,
        807,
        857,
        910,
        965,
        1022,
        1081,
        1143,
        1207,
        1274,
        1343,
        1414,
        1489,
        1565,
        1645,
        1735,
        1820,
        1908,
        2000,
        2094,
        2152,
        2212,
        2272,
        2333,
        2395,
        2462,
        2528,
        2597,
        2664,
        2735,
        2805,
        2878,
        2949,
        3026,
        3102,
        3152,
        3201,
        3252,
        3301,
        3352,
        3401,
        3453,
        3503,
        3554,
        3604,
        3656,
        3708,
        3760,
        3812,
        3865,
        3918,
        3970,
        4023,
        4076,
        4130,
        4180,
        4231,
        4283,
        4334,
        4381,
        4428,
        4476,
        4524,
        4572,
        4620
      ],
      "防御力": [
        100,
        100,
        100,
        100,
        100,
        100,
        100,
        100,
        100,
        100,
        100,
        100,
        100,
        100,
        100,
        100,
        100,
        100,
        100,
        100,
        100,
        100,
        100,
        100,
        100,
        100,
        100,
        100,
        100,
        100,
        100,
        100,
        100,
        100,
        100,
        100,
        100,
        100,
        100,
        100,
        100,
        100,
        100,
        100,
        100,
        100,
        100,
        100,
        100,
        100,
        100,
        100,
        100,
        100,
        100,
        100,
        100,
        100,
        100,
        100,
        100,
        100,
        100,
        100,
        100,
        100,
        100,
        100,
        100,
        100,
        100,
        100,
        100,
        100,
        100,
        100,
        100,
        100,
        100,
        100,
        100,
        100,
        100,
        100,
        100,
        100,
        100,
        100,
        100,
        100,
        100,
        100,
        100,
        100,
        100,
        100,
        100,
        100,
        100,
        100
      ]
    },
    {
      "enemyId": "eny_0071_sandb_settlement",
      "templateId": "eny_0071_sandb",
      "attrModifiers": "",
      "最大生命值": [
        1385,
        1580,
        1787,
        2006,
        2237,
        2626,
        3057,
        3534,
        4059,
        4635,
        4960,
        5291,
        5883,
        6511,
        7176,
        7876,
        8613,
        9051,
        9492,
        9936,
        10928,
        11998,
        13150,
        14389,
        15720,
        17149,
        18682,
        20467,
        22389,
        24457,
        27590,
        30361,
        33371,
        36640,
        40187,
        44032,
        48199,
        52709,
        57590,
        62869,
        68041,
        73547,
        79403,
        85626,
        92232,
        99239,
        106664,
        114528,
        122848,
        131644,
        143357,
        152574,
        162311,
        172595,
        183455,
        194921,
        207024,
        219799,
        233279,
        247504,
        262658,
        277803,
        294290,
        310746,
        327947,
        345031,
        363584,
        381990,
        404016,
        427763,
        443559,
        458756,
        475295,
        491199,
        508497,
        525125,
        543200,
        560567,
        579435,
        595357,
        623137,
        651842,
        681492,
        712106,
        743705,
        776307,
        809933,
        844605,
        880341,
        917164,
        939625,
        962441,
        985614,
        1009146,
        1024715,
        1040402,
        1056207,
        1072131,
        1088173,
        1104334
      ],
      "攻击力": [
        66,
        75,
        85,
        96,
        107,
        118,
        129,
        141,
        153,
        166,
        179,
        192,
        205,
        219,
        233,
        248,
        263,
        278,
        294,
        310,
        328,
        345,
        364,
        382,
        401,
        421,
        441,
        461,
        482,
        503,
        546,
        584,
        625,
        668,
        712,
        758,
        807,
        857,
        910,
        965,
        1022,
        1081,
        1143,
        1207,
        1274,
        1343,
        1414,
        1489,
        1565,
        1645,
        1735,
        1820,
        1908,
        2000,
        2094,
        2152,
        2212,
        2272,
        2333,
        2395,
        2462,
        2528,
        2597,
        2664,
        2735,
        2805,
        2878,
        2949,
        3026,
        3102,
        3152,
        3201,
        3252,
        3301,
        3352,
        3401,
        3453,
        3503,
        3554,
        3604,
        3656,
        3708,
        3760,
        3812,
        3865,
        3918,
        3970,
        4023,
        4076,
        4130,
        4180,
        4231,
        4283,
        4334,
        4381,
        4428,
        4476,
        4524,
        4572,
        4620
      ],
      "防御力": [
        100,
        100,
        100,
        100,
        100,
        100,
        100,
        100,
        100,
        100,
        100,
        100,
        100,
        100,
        100,
        100,
        100,
        100,
        100,
        100,
        100,
        100,
        100,
        100,
        100,
        100,
        100,
        100,
        100,
        100,
        100,
        100,
        100,
        100,
        100,
        100,
        100,
        100,
        100,
        100,
        100,
        100,
        100,
        100,
        100,
        100,
        100,
        100,
        100,
        100,
        100,
        100,
        100,
        100,
        100,
        100,
        100,
        100,
        100,
        100,
        100,
        100,
        100,
        100,
        100,
        100,
        100,
        100,
        100,
        100,
        100,
        100,
        100,
        100,
        100,
        100,
        100,
        100,
        100,
        100,
        100,
        100,
        100,
        100,
        100,
        100,
        100,
        100,
        100,
        100,
        100,
        100,
        100,
        100,
        100,
        100,
        100,
        100,
        100,
        100
      ]
    }
  ]
}